neuron_cli/__init__.py
neuron_cli/api_server.py
neuron_cli/version.py
neuron_cli/cli/__init__.py
neuron_cli/cli/main.py
neuron_cli/connection/__init__.py
neuron_cli/connection/detector.py
neuron_cli/connection/mesh_ip.py
neuron_cli/connection/websocket_client.py
neuron_cli/core/__init__.py
neuron_cli/core/agent.py
neuron_cli/core/config.py
neuron_cli/core/logger.py
neuron_cli/core/mesh_lock.py
neuron_cli/diagnostics/__init__.py
neuron_cli/hardware/__init__.py
neuron_cli/hardware/detector.py
neuron_cli/installer/__init__.py
neuron_cli/installer/dependency_installer.py
neuron_cli/installer/host_service.py
neuron_cli/installer/space_agent.py
neuron_cli/installer/system_detector.py
neuron_cli/iot/__init__.py
neuron_cli/jobs/__init__.py
neuron_cli/jobs/executor.py
neuron_cli/jobs/package_manager.py
neuron_cli/marketplace/__init__.py
neuron_cli/marketplace/manager.py
neuron_cli/marketplace/manifest.py
neuron_cli/monitoring/__init__.py
neuron_cli/monitoring/agent_benchmark.py
neuron_cli/monitoring/agent_telemetry.py
neuron_cli/monitoring/device_scanner.py
neuron_cli/monitoring/heartbeat.py
neuron_cli/monitoring/job_metrics.py
neuron_cli/monitoring/network_monitor.py
neuron_cli/monitoring/stats_collector.py
neuron_cli/monitoring/usage_metering.py
neuron_cli/network/__init__.py
neuron_cli/ollama/__init__.py
neuron_cli/ollama/manager.py
neuron_cli/plugins/__init__.py
neuron_cli/plugins/base.py
neuron_cli/security/__init__.py
neuron_cli/security/firewall.py
neuron_cli/services/__init__.py
neuron_cli/services/docker_manager.py
neuron_cli/services/host_manager.py
neuron_cli/services/manager.py
neuron_cli/submesh/__init__.py
neuron_cli/telemetry/__init__.py
neuron_cli/telemetry/collector.py
neuron_cli/telemetry/reporter.py
neuron_cli/updater/__init__.py
neuron_cli/updater/self_updater.py
san_cli-1.0.41.dist-info/METADATA
san_cli-1.0.41.dist-info/WHEEL
san_cli-1.0.41.dist-info/entry_points.txt
san_cli-1.0.41.dist-info/top_level.txt
san_cli-1.0.41.dist-info/RECORD
