Metadata-Version: 2.1
Name: san-cli
Version: 1.0.41
Summary: Space Agent Network CLI - Device management and OTP authentication
Home-page: https://github.com/Nexus-Core-Cloud/Nexus-Support-Tickets-AI
Author: NexusCore
Author-email: support@nexuscore.cloud
Project-URL: Bug Reports, https://github.com/Nexus-Core-Cloud/Nexus-Support-Tickets-AI/issues
Project-URL: Source, https://github.com/Nexus-Core-Cloud/Nexus-Support-Tickets-AI
Keywords: cli,device-management,otp,authentication,distributed-computing
Classifier: Development Status :: 4 - Beta
Classifier: Intended Audience :: Developers
Classifier: Intended Audience :: System Administrators
Classifier: Topic :: System :: Distributed Computing
Classifier: Topic :: System :: Systems Administration
Classifier: License :: OSI Approved :: MIT License
Classifier: Programming Language :: Python :: 3
Classifier: Programming Language :: Python :: 3.8
Classifier: Programming Language :: Python :: 3.9
Classifier: Programming Language :: Python :: 3.10
Classifier: Programming Language :: Python :: 3.11
Classifier: Programming Language :: Python :: 3.12
Classifier: Operating System :: OS Independent
Requires-Python: >=3.8
Requires-Dist: click >=8.0.0
Requires-Dist: flask-cors >=4.0.0
Requires-Dist: flask >=2.3.0
Requires-Dist: psutil >=5.9.0
Requires-Dist: pyyaml >=6.0.0
Requires-Dist: requests >=2.28.0
